Metadata-Version: 1.1
Name: python-project-bootstrap
Version: 0.1.5
Summary: Start your new python project with a ready to installdirectory and scripts structure
Home-page: https://github.com/royarzun/Python-project-bootstrap
Author: Ricardo Oyarzun
Author-email: royarzun@gmail.com
License: MIT License
